odoo10_addon_stock_disable_force_availability_button-10.0.1.0.0-py2.7-nspkg.pth
odoo/addons/stock_disable_force_availability_button/README.rst
odoo/addons/stock_disable_force_availability_button/__init__.py
odoo/addons/stock_disable_force_availability_button/__manifest__.py
odoo/addons/stock_disable_force_availability_button/i18n/pt_BR.po
odoo/addons/stock_disable_force_availability_button/i18n/sl.po
odoo/addons/stock_disable_force_availability_button/security/stock_disable_force_availability_button_security.xml
odoo/addons/stock_disable_force_availability_button/views/stock_view.xml
odoo10_addon_stock_disable_force_availability_button-10.0.1.0.0.dist-info/DESCRIPTION.rst
odoo10_addon_stock_disable_force_availability_button-10.0.1.0.0.dist-info/METADATA
odoo10_addon_stock_disable_force_availability_button-10.0.1.0.0.dist-info/RECORD
odoo10_addon_stock_disable_force_availability_button-10.0.1.0.0.dist-info/WHEEL
odoo10_addon_stock_disable_force_availability_button-10.0.1.0.0.dist-info/metadata.json
odoo10_addon_stock_disable_force_availability_button-10.0.1.0.0.dist-info/namespace_packages.txt
odoo10_addon_stock_disable_force_availability_button-10.0.1.0.0.dist-info/top_level.txt
